bayesvp/__init__.py
bayesvp/config.py
bayesvp/likelihood.py
bayesvp/mcmc_setup.py
bayesvp/utilities.py
bayesvp/vp_model.py
bayesvp/data/atom.dat
bayesvp/data/example/OVI.spec
bayesvp/data/example/True_logNs.dat
bayesvp/data/example/config_OVI.dat
bayesvp/scripts/__init__.py
bayesvp/scripts/bvp_process_model.py
bayesvp/scripts/bvp_write_config.py
bayesvp/scripts/bvpfit.py
bayesvp/tests/__init__.py
bayesvp/tests/run_tests.py
bayesvp/tests/test_config.py
bayesvp/tests/test_likelihood.py
bayesvp/tests/test_model.py
bayesvp-0.2.5.dist-info/LICENSE
bayesvp-0.2.5.dist-info/METADATA
bayesvp-0.2.5.dist-info/WHEEL
bayesvp-0.2.5.dist-info/entry_points.txt
bayesvp-0.2.5.dist-info/top_level.txt
bayesvp-0.2.5.dist-info/RECORD
