Metadata-Version: 2.1
Name: bayesvp
Version: 0.2.5
Summary: Bayesian MCMC Voigt Profile Fitting
Home-page: https://github.com/cameronliang/bayesvp
Author: Cameron Liang
Author-email: cameron.liang@gmail.com
License: MIT
Platform: UNKNOWN
Requires-Dist: numpy
Requires-Dist: scipy
Requires-Dist: matplotlib
Requires-Dist: kombine
Requires-Dist: emcee
